vision_agent/__init__.py
vision_agent/enhanced_server.py
vision_agent/main.py
vision_agent/server.py
vision_agent/agents/__init__.py
vision_agent/agents/async_base_agent.py
vision_agent/agents/async_classification_agent.py
vision_agent/agents/async_face_agent.py
vision_agent/agents/async_object_agent.py
vision_agent/agents/async_video_agent.py
vision_agent/agents/base_agent.py
vision_agent/agents/classification_agent.py
vision_agent/agents/enhanced_face_agent.py
vision_agent/agents/face_agent.py
vision_agent/agents/face_agent_opencv.py
vision_agent/agents/object_agent.py
vision_agent/agents/video_agent.py
vision_agent/core/__init__.py
vision_agent/core/byte_processing.py
vision_agent/core/canvas_interface.py
vision_agent/core/cost_predictor.py
vision_agent/core/predictive_scaling.py
vision_agent/core/token_recycling.py
vision_agent/core/vision_agent.py
vision_agent/servers/__init__.py
vision_agent/servers/async_server.py
vision_agent/servers/enhanced_server.py
vision_agent/servers/server.py
vision_agent/servers/simple_enhanced_server.py
vision_agent/utils/__init__.py
vision_agent/utils/caching.py
vision_agent/utils/config_advanced.py
vision_agent/utils/enhanced_base_agent.py
vision_agent/utils/helpers.py
vision_agent/utils/performance_analytics.py
vision_agent/utils/reliability.py
vision_agent/utils/resource_manager.py
vision_agent/utils/semantic_cache.py
vision_agent/utils/speculative_execution.py
vision_agent/utils/streaming.py
vision_agent/utils/tracing.py
vision_agent_framework-1.0.0.dist-info/METADATA
vision_agent_framework-1.0.0.dist-info/WHEEL
vision_agent_framework-1.0.0.dist-info/entry_points.txt
vision_agent_framework-1.0.0.dist-info/top_level.txt
vision_agent_framework-1.0.0.dist-info/RECORD
