Metadata-Version: 2.4
Name: vision-agent-framework
Version: 1.0.0
Summary: World-Class Multi-Modal AI Agent Framework with Revolutionary Performance Features
Home-page: https://github.com/krishna-bajpai/vision-agent
Download-URL: https://github.com/krishna-bajpai/vision-agent/archive/main.zip
Author: Krishna Bajpai, Vedanshi Gupta
Author-email: krishna@krishnabajpai.me, vedanshigupta158@gmail.com
Maintainer: Krishna Bajpai, Vedanshi Gupta
Maintainer-email: krishna.bajpai@example.com
Project-URL: Documentation, https://vision-agent.readthedocs.io
Project-URL: Bug Reports, https://github.com/krishna-bajpai/vision-agent/issues
Project-URL: Source, https://github.com/krishna-bajpai/vision-agent
Project-URL: Changelog, https://github.com/krishna-bajpai/vision-agent/blob/main/CHANGELOG.md
Keywords: ai,machine-learning,computer-vision,agent-framework,multi-modal,face-detection,object-detection,video-processing,fastapi,async,performance-optimization,enterprise,token-recycling,predictive-scaling,cost-prediction,canvas-interface,workflow-automation,differential-privacy
Platform: any
Classifier: Development Status :: 4 - Beta
Classifier: Intended Audience :: Developers
Classifier: Intended Audience :: Science/Research
Classifier: Intended Audience :: Information Technology
Classifier: Topic :: Software Development :: Libraries :: Python Modules
Classifier: Topic :: Scientific/Engineering :: Artificial Intelligence
Classifier: Topic :: Scientific/Engineering :: Image Processing
Classifier: Topic :: Multimedia :: Video
Classifier: Topic :: Internet :: WWW/HTTP :: HTTP Servers
Classifier: License :: OSI Approved :: MIT License
Classifier: Programming Language :: Python :: 3
Classifier: Programming Language :: Python :: 3.9
Classifier: Programming Language :: Python :: 3.10
Classifier: Programming Language :: Python :: 3.11
Classifier: Programming Language :: Python :: 3.12
Classifier: Operating System :: OS Independent
Classifier: Operating System :: POSIX :: Linux
Classifier: Operating System :: Microsoft :: Windows
Classifier: Operating System :: MacOS
Classifier: Framework :: AsyncIO
Classifier: Framework :: FastAPI
Classifier: Environment :: Web Environment
Classifier: Environment :: GPU :: NVIDIA CUDA
Classifier: Natural Language :: English
Requires-Python: >=3.9
Requires-Dist: fastapi>=0.104.0
Requires-Dist: uvicorn[standard]>=0.24.0
Requires-Dist: numpy>=1.24.0
Requires-Dist: opencv-python>=4.8.0
Requires-Dist: Pillow>=10.0.0
Requires-Dist: pydantic>=2.0.0
Requires-Dist: python-multipart>=0.0.6
Requires-Dist: aiofiles>=23.0.0
Requires-Dist: psutil>=5.9.0
Provides-Extra: ai
Requires-Dist: torch>=2.0.0; extra == "ai"
Requires-Dist: torchvision>=0.15.0; extra == "ai"
Requires-Dist: transformers>=4.35.0; extra == "ai"
Requires-Dist: ultralytics>=8.0.0; extra == "ai"
Requires-Dist: scikit-learn>=1.3.0; extra == "ai"
Requires-Dist: sentence-transformers>=2.2.0; extra == "ai"
Provides-Extra: advanced
Requires-Dist: redis>=5.0.0; extra == "advanced"
Requires-Dist: sqlalchemy>=2.0.0; extra == "advanced"
Requires-Dist: alembic>=1.12.0; extra == "advanced"
Requires-Dist: celery>=5.3.0; extra == "advanced"
Requires-Dist: prometheus-client>=0.19.0; extra == "advanced"
Requires-Dist: elastic-apm>=6.15.0; extra == "advanced"
Provides-Extra: dev
Requires-Dist: pytest>=7.4.0; extra == "dev"
Requires-Dist: pytest-asyncio>=0.21.0; extra == "dev"
Requires-Dist: pytest-cov>=4.1.0; extra == "dev"
Requires-Dist: black>=23.0.0; extra == "dev"
Requires-Dist: isort>=5.12.0; extra == "dev"
Requires-Dist: flake8>=6.0.0; extra == "dev"
Requires-Dist: mypy>=1.5.0; extra == "dev"
Requires-Dist: pre-commit>=3.4.0; extra == "dev"
Provides-Extra: full
Requires-Dist: torch>=2.0.0; extra == "full"
Requires-Dist: torchvision>=0.15.0; extra == "full"
Requires-Dist: transformers>=4.35.0; extra == "full"
Requires-Dist: ultralytics>=8.0.0; extra == "full"
Requires-Dist: scikit-learn>=1.3.0; extra == "full"
Requires-Dist: sentence-transformers>=2.2.0; extra == "full"
Requires-Dist: redis>=5.0.0; extra == "full"
Requires-Dist: sqlalchemy>=2.0.0; extra == "full"
Requires-Dist: alembic>=1.12.0; extra == "full"
Requires-Dist: celery>=5.3.0; extra == "full"
Requires-Dist: prometheus-client>=0.19.0; extra == "full"
Requires-Dist: elastic-apm>=6.15.0; extra == "full"
Provides-Extra: enterprise
Requires-Dist: torch>=2.0.0; extra == "enterprise"
Requires-Dist: torchvision>=0.15.0; extra == "enterprise"
Requires-Dist: transformers>=4.35.0; extra == "enterprise"
Requires-Dist: ultralytics>=8.0.0; extra == "enterprise"
Requires-Dist: scikit-learn>=1.3.0; extra == "enterprise"
Requires-Dist: sentence-transformers>=2.2.0; extra == "enterprise"
Requires-Dist: redis>=5.0.0; extra == "enterprise"
Requires-Dist: sqlalchemy>=2.0.0; extra == "enterprise"
Requires-Dist: alembic>=1.12.0; extra == "enterprise"
Requires-Dist: celery>=5.3.0; extra == "enterprise"
Requires-Dist: prometheus-client>=0.19.0; extra == "enterprise"
Requires-Dist: elastic-apm>=6.15.0; extra == "enterprise"
Requires-Dist: kubernetes>=24.0.0; extra == "enterprise"
Requires-Dist: docker>=6.1.0; extra == "enterprise"
Requires-Dist: boto3>=1.29.0; extra == "enterprise"
Requires-Dist: azure-storage-blob>=12.19.0; extra == "enterprise"
Requires-Dist: google-cloud-storage>=2.10.0; extra == "enterprise"
Dynamic: author
Dynamic: author-email
Dynamic: classifier
Dynamic: description
Dynamic: description-content-type
Dynamic: download-url
Dynamic: home-page
Dynamic: keywords
Dynamic: maintainer
Dynamic: maintainer-email
Dynamic: platform
Dynamic: project-url
Dynamic: provides-extra
Dynamic: requires-dist
Dynamic: requires-python
Dynamic: summary
